{
  "general": {
    "name": "Thorben Manns",
    "country": "de",
    "mtga_rank": {
      "constructed": "Diamond 4",
      "limited": "Platinum 4"
    },
    "win rate": "35.71%"
  },
  "sources": {
    "Unity League": {
      "url": "https://unityleague.gg/player/30761/",
      "data": {
        "name": "Thorben Manns",
        "photo": null,
        "country": "de",
        "local organizer": "Mulligan TCG Shop",
        "rank germany": "275",
        "rank europe": "2502",
        "rank points": "54",
        "record": "10-15-3",
        "win rate": "39.3%"
      }
    },
    "Untapped.gg": {
      "url": "https://mtga.untapped.gg/profile/26bc5895-e630-4e3c-85de-1ad6d62ed4b2/K4Q4M5EMSNB53KEKGXSKGOZEII",
      "data": {
        "mtga_rank": {
          "constructed": "Diamond 4",
          "limited": "Platinum 4"
        }
      }
    }
  }
}
